rasa_codeless/__init__.py
rasa_codeless/__main__.py
rasa_codeless/rasa_codeless.py
rasa_codeless/core/__init__.py
rasa_codeless/core/curve_explainer.py
rasa_codeless/core/training_queue.py
rasa_codeless/core/botstore/__init__.py
rasa_codeless/core/botstore/local_botstore.py
rasa_codeless/core/botstore/mongodb_botstore.py
rasa_codeless/server/__init__.py
rasa_codeless/server/rasac_server.py
rasa_codeless/server/frontend/asset-manifest.json
rasa_codeless/server/frontend/index.html
rasa_codeless/server/frontend/manifest.json
rasa_codeless/server/frontend/robots.txt
rasa_codeless/server/frontend/res/images/apple-touch-icon.png
rasa_codeless/server/frontend/res/images/favicon-16x16.png
rasa_codeless/server/frontend/res/images/favicon-32x32.png
rasa_codeless/server/frontend/res/images/favicon.ico
rasa_codeless/server/frontend/res/images/logo192.png
rasa_codeless/server/frontend/res/images/logo512.png
rasa_codeless/server/frontend/res/images/rasac.png
rasa_codeless/server/frontend/res/scripts/bootstrap.min.js
rasa_codeless/server/frontend/res/scripts/jquery-3.6.0.min.js
rasa_codeless/server/frontend/res/scripts/jquery.parallaxify.min.js
rasa_codeless/server/frontend/res/scripts/kbi-2.0.2.js
rasa_codeless/server/frontend/res/styles/app_styles.css
rasa_codeless/server/frontend/res/styles/bootstrap.min.css
rasa_codeless/server/frontend/res/styles/ghost.css
rasa_codeless/server/frontend/static/css/main.0ac5169c.css
rasa_codeless/server/frontend/static/css/main.0ac5169c.css.map
rasa_codeless/server/frontend/static/js/main.59a5b9f7.js
rasa_codeless/server/frontend/static/js/main.59a5b9f7.js.LICENSE.txt
rasa_codeless/server/frontend/static/js/main.59a5b9f7.js.map
rasa_codeless/server/frontend/static/media/rasac.fbeb3b13c3d78235b99e.png
rasa_codeless/server/rasac_api/__init__.py
rasa_codeless/server/rasac_api/routes.py
rasa_codeless/shared/__init__.py
rasa_codeless/shared/constants.py
rasa_codeless/shared/exceptions/__init__.py
rasa_codeless/shared/exceptions/base.py
rasac-2.1.1.dist-info/LICENSE
rasac-2.1.1.dist-info/METADATA
rasac-2.1.1.dist-info/WHEEL
rasac-2.1.1.dist-info/entry_points.txt
rasac-2.1.1.dist-info/top_level.txt
rasac-2.1.1.dist-info/RECORD
