Metadata-Version: 2.1
Name: rasac
Version: 2.1.1
Summary: A GUI for NLU pipeline configurations and model training for Rasa Conversational AIs.
Home-page: https://github.com/rasa-codeless/rasac
Author: Shamikh Hameed
Author-email: shamikhhameed@gmail.com
License: Apache License 2.0
Classifier: Development Status :: 5 - Production/Stable
Classifier: Environment :: Console
Classifier: Environment :: GPU
Classifier: Framework :: Flask
Classifier: Intended Audience :: Developers
Classifier: Intended Audience :: Education
Classifier: Intended Audience :: Science/Research
Classifier: License :: OSI Approved :: Apache Software License
Classifier: Operating System :: OS Independent
Classifier: Programming Language :: Python :: 3.7
Classifier: Programming Language :: Python :: 3.8
Classifier: Topic :: Scientific/Engineering :: Artificial Intelligence
License-File: LICENSE
Requires-Dist: rasa (~=2.8.8)
Requires-Dist: requests (<3.0,>=2.23)
Requires-Dist: regex (<2021.8,>=2020.6)
Requires-Dist: ruamel.yaml (<0.17.0,>=0.16.5)
Requires-Dist: numpy (<1.19,>=1.16)
Requires-Dist: tensorflow (<2.4,>=2.3.4)
Requires-Dist: pyyaml (~=6.0)
Requires-Dist: setuptools (>=41.0.0)
Requires-Dist: psutil (~=5.9.1)
Requires-Dist: flask (~=2.1.2)
Requires-Dist: waitress (~=2.1.2)
Requires-Dist: python-dotenv (~=0.20.0)
Requires-Dist: pymongo (~=3.10.1)
Requires-Dist: pandas (~=1.4.3)
